displaymath2equation/__init__.py
displaymath2equation/config.py
displaymath2equation/main.py
pandoc_displaymath2equation-0.0.0.3.dist-info/METADATA
pandoc_displaymath2equation-0.0.0.3.dist-info/WHEEL
pandoc_displaymath2equation-0.0.0.3.dist-info/entry_points.txt
pandoc_displaymath2equation-0.0.0.3.dist-info/licenses/LICENSE
pandoc_displaymath2equation-0.0.0.3.dist-info/RECORD
