Metadata-Version: 2.3
Name: pandoc-displaymath2equation
Version: 0.0.0.3
Summary: Automatically number display-math equations in pandoc.
Project-URL: Homepage, https://github.com/FynnFreyer/pandoc-displaymath2equation
Project-URL: Issues, https://github.com/FynnFreyer/pandoc-displaymath2equation/issues
Author-email: "Freyer, Fynn" <fynn.freyer@googlemail.com>
License-File: LICENSE
Classifier: Development Status :: 3 - Alpha
Classifier: License :: OSI Approved :: MIT License
Classifier: Programming Language :: Python :: 3.10
Classifier: Topic :: Text Processing
Classifier: Topic :: Text Processing :: Filters
Classifier: Topic :: Text Processing :: Markup
Classifier: Topic :: Text Processing :: Markup :: LaTeX
Requires-Python: >=3.10
Requires-Dist: panflute
Provides-Extra: dev
Requires-Dist: hatch; extra == 'dev'
Requires-Dist: mypy; extra == 'dev'
Requires-Dist: pip-tools; extra == 'dev'
Requires-Dist: pylint; extra == 'dev'
Requires-Dist: pytest; extra == 'dev'
